aireloom/__init__.py
aireloom/client.py
aireloom/config.py
aireloom/constants.py
aireloom/endpoints.py
aireloom/session.py
aireloom/unwrapper.py
aireloom/models/__init__.py
aireloom/models/base.py
aireloom/models/data_source.py
aireloom/models/organization.py
aireloom/models/project.py
aireloom/models/research_product.py
aireloom/models/scholix.py
aireloom/resources/__init__.py
aireloom/resources/base_client.py
aireloom/resources/data_sources_client.py
aireloom/resources/organizations_client.py
aireloom/resources/projects_client.py
aireloom/resources/research_products_client.py
aireloom/resources/scholix_client.py
aireloom-0.1.0.dist-info/METADATA
aireloom-0.1.0.dist-info/WHEEL
aireloom-0.1.0.dist-info/RECORD
