Metadata-Version: 2.4
Name: aireloom
Version: 0.1.0
Summary: Python interface for the OpenAIRE Graph API, built on top of the bibliofabric framework.
Project-URL: Homepage, https://github.com/utsmok/aireloom
Author-email: Samuel Mok <s.mok@utwente.nl>
License: MIT
Requires-Python: >=3.12
Requires-Dist: bibliofabric
Requires-Dist: certifi
Provides-Extra: analysis
Requires-Dist: duckdb>=1.3.0; extra == 'analysis'
Requires-Dist: matplotlib>=3.10.3; extra == 'analysis'
Requires-Dist: networkx>=3.5; extra == 'analysis'
Requires-Dist: numpy>=2.3.0; extra == 'analysis'
Requires-Dist: pandas>=2.3.0; extra == 'analysis'
Requires-Dist: plotly>=6.1.2; extra == 'analysis'
Requires-Dist: polars; extra == 'analysis'
Requires-Dist: pyarrow>=20.0.0; extra == 'analysis'
Requires-Dist: requests>=2.32.4; extra == 'analysis'
Requires-Dist: rich>=14.0.0; extra == 'analysis'
Requires-Dist: seaborn>=0.13.2; extra == 'analysis'
